exploit_sensei/__init__.py
exploit_sensei/cli.py
exploit_sensei/llm.py
exploit_sensei/version.py
exploit_sensei-0.1.6.dist-info/METADATA
exploit_sensei-0.1.6.dist-info/WHEEL
exploit_sensei-0.1.6.dist-info/entry_points.txt
exploit_sensei-0.1.6.dist-info/RECORD
