Metadata-Version: 2.4
Name: exploit-sensei
Version: 0.1.6
Summary: LLM-powered exploitation recommendation tool
Project-URL: Homepage, https://github.com/hideckies/exploit-sensei
Project-URL: Documentation, https://github.com/hideckies/exploit-sensei
Project-URL: Repository, https://github.com/hideckies/exploit-sensei.git
Project-URL: Issues, https://github.com/hideckies/exploit-sensei/issues
Author-email: hdks <hdks.bug@gmail.com>
Requires-Python: >=3.11
Requires-Dist: click>=8.1.8
Requires-Dist: openai>=1.66.3
Requires-Dist: rich>=13.9.4
Requires-Dist: ruff>=0.10.0
